{
  "ngrok_url": "https://reverb-verse-unnamable.ngrok-free.dev",
  "webhook_ok": true,
  "webhook_url": "https://reverb-verse-unnamable.ngrok-free.dev/webhook",
  "last_signal": {
    "action": "SELL",
    "entry": 4832.1,
    "lots": 1.3,
    "signal_type": "SELL_TREND",
    "sl": 4835.62,
    "source": "v15F",
    "status": "pending",
    "symbol": "XAUUSD",
    "timestamp": "2026-04-18 02:26:01.167730",
    "tp": 4821.54,
    "tp1": 4830.34,
    "tp2": 4821.54
  },
  "alert_count": 200,
  "updated": "2026-04-18 03:22:43.961319"
}