{
  "generated_at": "2026-04-17T13:00:49.910401",
  "period": "Since inception",
  "summary": {
    "total_trades": 2,
    "wins": 1,
    "losses": 1,
    "open_trades": 5,
    "win_rate": 50.0,
    "profit_factor": 3.0,
    "net_pnl": 1888.53,
    "gross_profit": 2831.63,
    "gross_loss": 943.1,
    "balance": 89040.29,
    "peak_balance": 97219.37,
    "drawdown_pct": 8.41,
    "return_pct": 790.4,
    "avg_win": 2831.63,
    "avg_loss": 943.1,
    "max_consec_wins": 1,
    "max_consec_losses": 1,
    "today_pnl": 0
  },
  "best_trade": {
    "id": 1,
    "signal": "SELL",
    "signal_type": "SELL_TREND",
    "strategy": "v15F_M5",
    "entry_price": 4805.69,
    "entry_time": "2026-04-15 14:40:02.557577",
    "sl": 4811.24,
    "tp": 4789.03,
    "lot_size": 1.7,
    "risk_amount": 943.88,
    "status": "closed",
    "exit_price": 4788.76,
    "exit_time": "2026-04-16 02:18:36.575777",
    "reason": "TP",
    "pnl": 2831.63,
    "result": "win",
    "balance_after": 97219.37
  },
  "worst_trade": {
    "id": 1,
    "signal": "SELL",
    "signal_type": "SELL_REVERSAL",
    "strategy": "v15F_M5",
    "entry_price": 4814.99,
    "entry_time": "2026-04-16 14:45:57.227316",
    "sl": 4818.7,
    "tp": 4803.87,
    "lot_size": 2.54,
    "risk_amount": 943.1,
    "status": "closed",
    "exit_price": 4819.04,
    "exit_time": "2026-04-16 16:34:01.929170",
    "reason": "SL",
    "pnl": -943.1,
    "result": "loss",
    "balance_after": 93366.82
  },
  "daily_pnl": {
    "2026-04-15": 2831.63,
    "2026-04-16": -943.1
  },
  "open_trades": [
    {
      "ticket": 1181489553,
      "symbol": "XAUUSD",
      "type": "SELL",
      "volume": 0.42,
      "open_price": 4787.21,
      "current": 4791.29,
      "sl": 4807.93,
      "tp": 4725.05,
      "profit": -171.36,
      "magic": 20260410,
      "time": "2026-04-17 14:48:23"
    },
    {
      "ticket": 1181492183,
      "symbol": "XAUUSD",
      "type": "SELL",
      "volume": 0.42,
      "open_price": 4785.68,
      "current": 4791.29,
      "sl": 4806.53,
      "tp": 4723.65,
      "profit": -235.62,
      "magic": 20260410,
      "time": "2026-04-17 14:48:34"
    },
    {
      "ticket": 1181562726,
      "symbol": "XAUUSD",
      "type": "SELL",
      "volume": 0.42,
      "open_price": 4782.28,
      "current": 4791.29,
      "sl": 4803.21,
      "tp": 4720.33,
      "profit": -378.42,
      "magic": 20260410,
      "time": "2026-04-17 15:03:58"
    },
    {
      "ticket": 1181573083,
      "symbol": "XAUUSD",
      "type": "SELL",
      "volume": 0.42,
      "open_price": 4781.06,
      "current": 4791.29,
      "sl": 4801.8,
      "tp": 4718.92,
      "profit": -429.66,
      "magic": 20260410,
      "time": "2026-04-17 15:06:38"
    },
    {
      "ticket": 1181608320,
      "symbol": "XAUUSD",
      "type": "SELL",
      "volume": 0.42,
      "open_price": 4784.86,
      "current": 4791.29,
      "sl": 4805.57,
      "tp": 4722.69,
      "profit": -270.06,
      "magic": 20260410,
      "time": "2026-04-17 15:12:08"
    }
  ]
}